{
  "_comment": "Farben und Icons für jedes Fach. Ordnername = Key. Neue Fächer hier eintragen. Mission 8 (2026-05-07): icon-Werte sind ab jetzt Lucide-Icon-Namen (siehe assets/js/icons.js). iconType:'lucide' lässt den Renderer lfIcon() benutzen statt das Feld als Emoji zu rendern. User-Custom-Icons in userData.settings.customIcons bleiben weiterhin Emoji.",

  "Mathematik": {
    "name":  "Mathematik",
    "color": "#3b82f6",
    "icon":  "sigma",
    "iconType": "lucide",
    "tools": { "calculator": true }
  },
  "Deutsch": {
    "name":  "Deutsch",
    "color": "#ef4444",
    "icon":  "book-open-text",
    "iconType": "lucide"
  },
  "_comment_englisch": "Mission 8 Q2-Override: Schueler erkennt UK-Flagge schneller als Globe. Flag-Icon ueber lipis/flag-icons (MIT), gerendert via lfFlag(). Hardcoded Farben (red/white/blue) — Theme-Tinting bewusst NICHT, sonst keine Flagge mehr.",
  "Englisch": {
    "name": "Englisch",
    "color": "#f7bc0a",
    "icon": "gb",
    "iconType": "flag"
  },
  "Geschichte": {
    "name":  "Geschichte",
    "color": "#f59e0b",
    "icon":  "landmark",
    "iconType": "lucide"
  },
  "Biologie": {
    "name":  "Biologie",
    "color": "#10b981",
    "icon":  "leaf",
    "iconType": "lucide"
  },
  "Latein": {
    "_note": "Mission 8 bug-fix per Adrian Q3: Latein hatte vorher dasselbe Icon+Color wie Biologie. Jetzt scroll-text + Lila (a78bfa). Maya kann Farbe overriden falls gewünscht.",
    "name":  "Latein",
    "color": "#a78bfa",
    "icon":  "scroll-text",
    "iconType": "lucide"
  },
  "Chemie": {
    "name":  "Chemie",
    "color": "#14b8a6",
    "icon":  "flask-conical",
    "iconType": "lucide",
    "tools": { "tafelwerk": true }
  },
  "Physik": {
    "name":  "Physik",
    "color": "#6366f1",
    "icon":  "atom",
    "iconType": "lucide",
    "tools": { "tafelwerk": true }
  },
  "Geographie": {
    "name":  "Geographie",
    "color": "#84cc16",
    "icon":  "map",
    "iconType": "lucide"
  },
  "Informatik": {
    "_note": "Maya's spec hatte 'code-2' aber Lucide hat das umbenannt zu 'code'. Verified via raw.githubusercontent.com (2026-05-07).",
    "name":  "Informatik",
    "color": "#06b6d4",
    "icon":  "code",
    "iconType": "lucide"
  },
  "Musik": {
    "name":  "Musik",
    "color": "#ec4899",
    "icon":  "music",
    "iconType": "lucide"
  },
  "Kunst": {
    "name":  "Kunst",
    "color": "#f97316",
    "icon":  "palette",
    "iconType": "lucide"
  },
  "Sport": {
    "name":  "Sport",
    "color": "#eab308",
    "icon":  "dumbbell",
    "iconType": "lucide"
  },
  "Politische-Bildung": {
    "_note": "Mega-Update 2026-05-09: PB neu hinzugefuegt. Color #0ea5e9 (sky-500) — distinkt von Informatik-Cyan #06b6d4 (klar blauer, weniger gruenstichig). Icon-Fallback: spec wollte 'landmark-2' (existiert nicht in icons.js) bzw. 'vote' (auch nicht da); 'landmark' ist bereits von Geschichte belegt. Stattdessen 'users-round' — passt zu Civic/Buergergesellschaft/Wahlen-Themen und ist im Map verfuegbar.",
    "name":  "Politische-Bildung",
    "color": "#0ea5e9",
    "icon":  "users-round",
    "iconType": "lucide"
  },
  "LER": {
    "_note": "Mega-Update 2026-05-09: LER (Lebensgestaltung-Ethik-Religionskunde) neu. Color #a855f7 (purple-500) — bewusst aehnliche Lila-Hue wie Latein #a78bfa, aber separates Fach, daher Naehe OK; #a855f7 ist saturierter/dunkler. Icon-Fallback: spec wollte 'heart-handshake' (nicht in icons.js); 'heart' ist die naechstgelegene verfuegbare Option und passt zu Ethik/Mitgefuehl/Religion-Vergleich.",
    "name":  "LER",
    "color": "#a855f7",
    "icon":  "heart",
    "iconType": "lucide"
  },
  "Arbeitslehre": {
    "_note": "Mega-Update 2026-05-09 Round 2 (Sophie-Audit): Color upgraded #737373 → #92400e (amber-800, deep workshop-brown). Grund: neutral-500 hatte ~3.0:1 Kontrast auf dunklen Themes (washed-out vs. die anderen 15 Faecher). Brown signalisiert WAT/Werken/Handwerk semantisch und faellt in einen leeren Hue-Slot — kein anderes Fach sitzt im tiefen Erd-Braun. Icon-Fallback: spec wollte 'briefcase' (nicht in icons.js); 'hammer' ist beste verfuegbare Option (Werken/praktische Arbeit/Handwerk) und nicht anderswo belegt.",
    "name":  "Arbeitslehre",
    "color": "#92400e",
    "icon":  "hammer",
    "iconType": "lucide"
  }
}
